t1est/__init__.py
t1est/t1est.py
t1est/examples/__init__.py
t1est/examples/basic_usage.py
t1est/examples/real_data.py
t1est/examples/bakeoff/__init__.py
t1est/examples/bakeoff/bakeoff.py
t1est/examples/bakeoff/loader.py
t1est-0.1.2.dist-info/LICENSE
t1est-0.1.2.dist-info/METADATA
t1est-0.1.2.dist-info/WHEEL
t1est-0.1.2.dist-info/top_level.txt
t1est-0.1.2.dist-info/RECORD
