Metadata-Version: 2.1
Name: t1est
Version: 0.1.2
Summary: Basic T1 fitting
Home-page: https://github.com/mckib2/t1est
Author: Nicholas McKibben
Author-email: nicholas.bgp@gmail.com
License: GPLv3
Platform: UNKNOWN
Requires-Python: >=3.6
Requires-Dist: numpy (>=1.17.2)
Requires-Dist: matplotlib (>=3.1.1)
Requires-Dist: phantominator (>=0.4.3)
Requires-Dist: tqdm (>=4.36.1)
